glpi_grafana_exporter/__init__.py
glpi_grafana_exporter/fake.py
glpi_grafana_exporter-0.0.1.dist-info/METADATA
glpi_grafana_exporter-0.0.1.dist-info/WHEEL
glpi_grafana_exporter-0.0.1.dist-info/entry_points.txt
glpi_grafana_exporter-0.0.1.dist-info/licenses/LICENSE
glpi_grafana_exporter-0.0.1.dist-info/RECORD
