Metadata-Version: 2.4
Name: glpi_grafana_exporter
Version: 0.0.1
Summary: Export GLPI statistics into Grafana (Grafana Cloud)
Project-URL: Homepage, https://github.com/yaroslaff/glpi-grafana-exporter
Project-URL: Issues, https://github.com/yaroslaff/glpi-grafana-exporter/issues
Author-email: Yaroslav Polyakov <yaroslaff@gmail.com>
License: MIT License
License-File: LICENSE
Classifier: License :: OSI Approved :: MIT License
Classifier: Operating System :: OS Independent
Classifier: Programming Language :: Python :: 3
Requires-Python: >=3.8
Requires-Dist: python-dotenv
Requires-Dist: sqlalchemy
Provides-Extra: mysql
Requires-Dist: mysqlclient; extra == 'mysql'
Provides-Extra: postgresql
Requires-Dist: psycopg2; extra == 'postgresql'
